pyshoper/__init__.py
pyshoper/api.py
pyshoper/api_helpers.py
pyshoper/client.py
pyshoper-0.1.2.dist-info/LICENSE
pyshoper-0.1.2.dist-info/WHEEL
pyshoper-0.1.2.dist-info/METADATA
pyshoper-0.1.2.dist-info/RECORD
