Metadata-Version: 2.1
Name: pyshoper
Version: 0.1.2
Summary: Python client to shoper.pl REST api
Home-page: https://github.com/przlada/pyshoper
License: UNKNOWN
Author: Przemysław Łada
Author-email: przlada@gmail.com
Requires-Python: >=3.5
Classifier: License :: OSI Approved :: MIT License
Requires-Dist: backoff
Requires-Dist: certifi
Requires-Dist: chardet
Requires-Dist: idna
Requires-Dist: requests
Requires-Dist: uplink
Requires-Dist: uritemplate
Requires-Dist: urllib3
Requires-Dist: pytest; extra == "test"
Provides-Extra: .none
Provides-Extra: test
